pypalp.pypy39-pp73-x86_64-linux-gnu.so
pypalp-0.1.0.dist-info/RECORD
pypalp-0.1.0.dist-info/METADATA
pypalp-0.1.0.dist-info/WHEEL
pypalp-0.1.0.dist-info/licenses/LICENSE
